bqmail/__init__.py
bqmail/mail.py
bqmail/query.py
bqmail-2.0.7.dist-info/METADATA
bqmail-2.0.7.dist-info/WHEEL
bqmail-2.0.7.dist-info/entry_points.txt
bqmail-2.0.7.dist-info/top_level.txt
bqmail-2.0.7.dist-info/RECORD
