Metadata-Version: 2.1
Name: bqmail
Version: 2.0.7
Summary: UNKNOWN
Home-page: https://git.nju.edu.cn/xumi1993/bqmail2.0
Author: Mijian Xu
Author-email: gomijianxu@gmail.com
License: GPLv3
Platform: UNKNOWN
Requires-Dist: obspy
Requires-Dist: pandas
